[
  {
    "id": 1,
    "state": "NEW",
    "serialNumber": "ABC-134",
    "model": "V1",
    "address": "ул. Пушкина",
    "gpsCoordinate": {
      "latitude": 34,
      "longitude": 25
    },
    "zone": {
      "gpsCoordinate": {
        "latitude": 76,
        "longitude": 158
      },
      "address": "Russia",
      "vrpDetectionArea": [
        {
          "x": 2345,
          "y": 1286
        },
        {
          "x": 3125,
          "y": 2915
        }
      ]
    }
  },
  {
    "id": 2,
    "state": "SETUP",
    "serialNumber": "XYZ-281",
    "model": "V2",
    "address": "ул. Лермонтова",
    "gpsCoordinate": {
      "latitude": 45,
      "longitude": 16
    },
    "zone": {
      "gpsCoordinate": {
        "latitude": 68,
        "longitude": 129
      },
      "address": "Russia",
      "vrpDetectionArea": [
        {
          "x": 2495,
          "y": 1891
        },
        {
          "x": 3413,
          "y": 2714
        }
      ]
    }
  }
]